kedro_snowflake/__init__.py
kedro_snowflake/cli.py
kedro_snowflake/cli_functions.py
kedro_snowflake/config.py
kedro_snowflake/datasets/__init__.py
kedro_snowflake/datasets/internal.py
kedro_snowflake/datasets/native.py
kedro_snowflake/generator.py
kedro_snowflake/misc.py
kedro_snowflake/pipeline.py
kedro_snowflake/runner.py
kedro_snowflake/starters/snowflights/README.md
kedro_snowflake/starters/snowflights/cookiecutter.json
kedro_snowflake/starters/snowflights/images/pipeline_visualisation_with_layers.png
kedro_snowflake/starters/snowflights/pipeline_visualisation_with_layers.png
kedro_snowflake/starters/snowflights/prompts.yml
kedro_snowflake/starters/snowflights/{{ cookiecutter.repo_name }}/.gitignore
kedro_snowflake/starters/snowflights/{{ cookiecutter.repo_name }}/README.md
kedro_snowflake/starters/snowflights/{{ cookiecutter.repo_name }}/conf/README.md
kedro_snowflake/starters/snowflights/{{ cookiecutter.repo_name }}/conf/base/catalog.yml
kedro_snowflake/starters/snowflights/{{ cookiecutter.repo_name }}/conf/base/logging.yml
kedro_snowflake/starters/snowflights/{{ cookiecutter.repo_name }}/conf/base/parameters/data_processing.yml
kedro_snowflake/starters/snowflights/{{ cookiecutter.repo_name }}/conf/base/parameters/data_science.yml
kedro_snowflake/starters/snowflights/{{ cookiecutter.repo_name }}/conf/base/parameters.yml
kedro_snowflake/starters/snowflights/{{ cookiecutter.repo_name }}/conf/base/snowflake.yml
kedro_snowflake/starters/snowflights/{{ cookiecutter.repo_name }}/conf/local/.gitkeep
kedro_snowflake/starters/snowflights/{{ cookiecutter.repo_name }}/conf/local/credentials.yml
kedro_snowflake/starters/snowflights/{{ cookiecutter.repo_name }}/data/01_raw/.gitkeep
kedro_snowflake/starters/snowflights/{{ cookiecutter.repo_name }}/data/01_raw/companies.csv
kedro_snowflake/starters/snowflights/{{ cookiecutter.repo_name }}/data/01_raw/reviews.csv
kedro_snowflake/starters/snowflights/{{ cookiecutter.repo_name }}/data/01_raw/shuttles.xlsx
kedro_snowflake-0.2.1.dist-info/LICENSE
kedro_snowflake-0.2.1.dist-info/METADATA
kedro_snowflake-0.2.1.dist-info/WHEEL
kedro_snowflake-0.2.1.dist-info/entry_points.txt
kedro_snowflake-0.2.1.dist-info/RECORD
