Metadata-Version: 2.1
Name: kedro-snowflake
Version: 0.2.1
Summary: Kedro plugin with Snowflake / Snowpark support
Home-page: https://github.com/getindata/kedro-snowflake
License: Apache-2.0
Keywords: kedro,snowflake,snowpark,mlops
Author: GetInData MLOPS
Author-email: mlops@getindata.com
Maintainer: GetInData MLOPS
Maintainer-email: mlops@getindata.com
Requires-Python: >=3.8,<3.9
Classifier: Development Status :: 4 - Beta
Classifier: License :: OSI Approved :: Apache Software License
Classifier: Programming Language :: Python :: 3
Classifier: Programming Language :: Python :: 3.8
Requires-Dist: backoff (>=2.2.1,<3.0.0)
Requires-Dist: cloudpickle (>=1.6.0,<=2.0.0)
Requires-Dist: kedro (>=0.18.7,<=0.18.8)
Requires-Dist: kedro-datasets[pandas-csvdataset,pandas-exceldataset,pandas-parquetdataset,snowflake-snowparktabledataset] (>=1.1.0)
Requires-Dist: pandas (>=1.3,<3.0)
Requires-Dist: pydantic (>=1.10.7,<2.0.0)
Requires-Dist: snowflake-snowpark-python[pandas] (>=1.0.0,<1.1.0)
Requires-Dist: tabulate (>=0.9.0,<0.10.0)
Requires-Dist: zstandard (>=0.20.0,<0.21.0)
Project-URL: Documentation, https://kedro-snowflake.readthedocs.io/
Project-URL: Repository, https://github.com/getindata/kedro-snowflake
